gromacs_helix/__init__.py
gromacs_helix/__main__.py
gromacs_helix/main.py
gromacs_helix-0.2.1.dist-info/METADATA
gromacs_helix-0.2.1.dist-info/WHEEL
gromacs_helix-0.2.1.dist-info/entry_points.txt
gromacs_helix-0.2.1.dist-info/RECORD
