Metadata-Version: 2.1
Name: gromacs-helix
Version: 0.2.1
Summary: 
Author: younthing
Author-email: fanxingfu3344@gmail.com
Requires-Python: >=3.11,<4.0
Classifier: Programming Language :: Python :: 3
Classifier: Programming Language :: Python :: 3.11
Classifier: Programming Language :: Python :: 3.12
Requires-Dist: typer[all] (>=0.12.3,<0.13.0)
